business_central_kon/__init__.py
business_central_kon/client.py
business_central_kon/services.py
business_central_kon/session.py
business_central_kon-1.0.0.dist-info/METADATA
business_central_kon-1.0.0.dist-info/WHEEL
business_central_kon-1.0.0.dist-info/licenses/LICENSE
business_central_kon-1.0.0.dist-info/RECORD
