Metadata-Version: 2.4
Name: business-central-kon
Version: 1.0.0
Summary: Business Central SDK for KSPPL
Author-email: Akshay Prabhu <prabhuakshay9803@gmail.com>
License-File: LICENSE
Requires-Python: >=3.12
Requires-Dist: arrow>=1.3.0
Requires-Dist: loguru>=0.7.2
Requires-Dist: openpyxl>=3.1.5
Requires-Dist: pandas>=2.2.3
Requires-Dist: pytest>=8.3.4
Requires-Dist: requests>=2.32.3
